cg/pyclang/__init__.py
cg/pyclang/py.typed
cg_pyclang-0.0.1.dist-info/METADATA
cg_pyclang-0.0.1.dist-info/LICENSE.md
cg_pyclang-0.0.1.dist-info/WHEEL
cg_pyclang-0.0.1.dist-info/RECORD
